pytago/__init__.py
pytago/app.py
pytago/cmd.py
pytago/core.py
pytago/go_ast/__init__.py
pytago/go_ast/ast_snippets.py
pytago/go_ast/core.py
pytago/go_ast/parsing.py
pytago/go_ast/py_snippets.py
pytago/go_ast/transformers.py
pytago-0.0.12.dist-info/LICENSE
pytago-0.0.12.dist-info/METADATA
pytago-0.0.12.dist-info/WHEEL
pytago-0.0.12.dist-info/entry_points.txt
pytago-0.0.12.dist-info/top_level.txt
pytago-0.0.12.dist-info/RECORD
