Metadata-Version: 2.1
Name: pytago
Version: 0.0.12
Summary: Transpiles some Python into human-readable Golang.
Home-page: https://github.com/nottheswimmer/pytago
Author: Michael Phelps
Author-email: michaelphelps@nottheswimmer.org
License: UNKNOWN
Platform: UNKNOWN
Classifier: Programming Language :: Python :: 3
Classifier: License :: OSI Approved :: MIT License
Classifier: Operating System :: OS Independent
Requires-Python: >=3.10
License-File: LICENSE
Requires-Dist: astroid (==2.6.2)
